README.md
setup.py
goback/__init__.py
goback/main.py
goback.egg-info/PKG-INFO
goback.egg-info/SOURCES.txt
goback.egg-info/dependency_links.txt
goback.egg-info/entry_points.txt
goback.egg-info/not-zip-safe
goback.egg-info/requires.txt
goback.egg-info/top_level.txt