Metadata-Version: 1.0
Name: goback
Version: 0.0.4
Summary: It helps you to navigate to the first few commits of a project on GitHub.
Home-page: https://github.com/zhoudaxia233/GoBack
Author: Zheng Zhou
Author-email: yootaoo@gmail.com
License: MIT
Keywords: github-helper
Platform: UNKNOWN
